Metadata-Version: 2.1
Name: bracket
Version: 0.1.3
Summary: Bracket is an Elegant static site generator.
Home-page: https://github.com/bracketing/bracket/
Author: Ceorleorn
Author-email: snbck@qq.com
License: MIT
Platform: UNKNOWN
Classifier: Programming Language :: Python :: 3
Classifier: License :: OSI Approved :: MIT License
Classifier: Operating System :: OS Independent
